{"data":{"markdownRemark":{"html":"<p>Podcasts dedicated to React and individual podcast episodes with React discussions.</p>\n<h2 id=\"podcasts\"><a href=\"#podcasts\" aria-hidden=\"true\" class=\"anchor\"><svg aria-hidden=\"true\" height=\"16\" version=\"1.1\" viewBox=\"0 0 16 16\" width=\"16\"><path fill-rule=\"evenodd\" d=\"M4 9h1v1H4c-1.5 0-3-1.69-3-3.5S2.55 3 4 3h4c1.45 0 3 1.69 3 3.5 0 1.41-.91 2.72-2 3.25V8.59c.58-.45 1-1.27 1-2.09C10 5.22 8.98 4 8 4H4c-.98 0-2 1.22-2 2.5S3 9 4 9zm9-3h-1v1h1c1 0 2 1.22 2 2.5S13.98 12 13 12H9c-.98 0-2-1.22-2-2.5 0-.83.42-1.64 1-2.09V6.25c-1.09.53-2 1.84-2 3.25C6 11.31 7.55 13 9 13h4c1.45 0 3-1.69 3-3.5S14.5 6 13 6z\"></path></svg></a>Podcasts</h2>\n<ul>\n<li>\n<p><a href=\"http://reactpodcast.com\">The React Podcast</a> - The podcast about everything React.js, hosted by <a href=\"https://reacttraining.com\">React Training</a></p>\n</li>\n<li>\n<p><a href=\"https://javascriptair.com/\">JavaScript Air</a> - All about JavaScript (currently not producing new episodes)</p>\n</li>\n<li>\n<p><a href=\"https://react30.com/\">React 30</a> - A 30-minute podcast all about React (moved to <a href=\"http://reactpodcast.com\">The React Podcast</a>).</p>\n</li>\n<li>\n<p><a href=\"https://devchat.tv/react-native-radio\">React Native Radio</a></p>\n</li>\n</ul>\n<h2 id=\"episodes\"><a href=\"#episodes\" aria-hidden=\"true\" class=\"anchor\"><svg aria-hidden=\"true\" height=\"16\" version=\"1.1\" viewBox=\"0 0 16 16\" width=\"16\"><path fill-rule=\"evenodd\" d=\"M4 9h1v1H4c-1.5 0-3-1.69-3-3.5S2.55 3 4 3h4c1.45 0 3 1.69 3 3.5 0 1.41-.91 2.72-2 3.25V8.59c.58-.45 1-1.27 1-2.09C10 5.22 8.98 4 8 4H4c-.98 0-2 1.22-2 2.5S3 9 4 9zm9-3h-1v1h1c1 0 2 1.22 2 2.5S13.98 12 13 12H9c-.98 0-2-1.22-2-2.5 0-.83.42-1.64 1-2.09V6.25c-1.09.53-2 1.84-2 3.25C6 11.31 7.55 13 9 13h4c1.45 0 3-1.69 3-3.5S14.5 6 13 6z\"></path></svg></a>Episodes</h2>\n<ul>\n<li><a href=\"http://codewinds.com/podcast/004.html\">CodeWinds Episode 4</a> - Pete Hunt talks with Jeff Barczewski about React.</li>\n</ul>\n<ul>\n<li><a href=\"https://devchat.tv/js-jabber/073-jsj-react-with-pete-hunt-and-jordan-walke\">JavaScript Jabber 73</a> - Pete Hunt and Jordan Walke talk about React.</li>\n</ul>","frontmatter":{"title":"Podcasts","next":null,"prev":null},"fields":{"path":"community/podcasts.md","slug":"community/podcasts.html"}}},"pathContext":{"slug":"community/podcasts.html"}}